consol/__init__.py
consol/confidence_models.py
consol/confident_solver.py
consol/main.py
consol/output_formats.py
consol-0.3.0.dist-info/METADATA
consol-0.3.0.dist-info/WHEEL
consol-0.3.0.dist-info/entry_points.txt
consol-0.3.0.dist-info/top_level.txt
consol-0.3.0.dist-info/RECORD
