Metadata-Version: 2.1
Name: consol
Version: 0.3.0
Summary: Confident Solver enables you to solve problems confidently and efficiently by leveraging Large Language Models (LLMs) enhanced with robust statistical approaches, such as the SPRT
Home-page: https://github.com/LiuzLab/consol
Author: ['Jaeyeon Lee', 'Hyun-Hwan Jeong']
Author-email: ['Jaeyeon.Lee@bcm.edu', 'hyun-hwan.jeong@bcm.edu']
Requires-Python: >=3.11.0
Requires-Dist: python-dotenv
Requires-Dist: scipy
Requires-Dist: pandas
Requires-Dist: langchain (>=0.3.14)
Requires-Dist: langchain-openai (>=0.2.2)
Requires-Dist: langchain-ollama (>=0.2.3)
Requires-Dist: langchain-google-genai (>=2.1.0)
